tapoapi/__init__.py
tapoapi/camera.py
tapoapi/py.typed
tapoapi-0.1.0.dist-info/licenses/LICENSE
tapoapi-0.1.0.dist-info/METADATA
tapoapi-0.1.0.dist-info/WHEEL
tapoapi-0.1.0.dist-info/top_level.txt
tapoapi-0.1.0.dist-info/RECORD
