Metadata-Version: 2.4
Name: tapoapi
Version: 0.1.0
Summary: Unofficial TP-Link Tapo local API client
Author: Jonathan Weiss
License-Expression: MIT
Project-URL: Repository, https://github.com/WhiteMCWizard/tapoapi
Project-URL: Issues, https://github.com/WhiteMCWizard/tapoapi/issues
Keywords: tapo,tp-link,tapo camera,iot,camera
Classifier: Programming Language :: Python :: 3
Classifier: Programming Language :: Python :: 3 :: Only
Classifier: Programming Language :: Python :: 3.9
Classifier: Programming Language :: Python :: 3.10
Classifier: Programming Language :: Python :: 3.11
Classifier: Programming Language :: Python :: 3.12
Classifier: Operating System :: OS Independent
Classifier: Development Status :: 3 - Alpha
Classifier: Topic :: Home Automation
Classifier: Typing :: Typed
Requires-Python: >=3.9
License-File: LICENSE
Requires-Dist: requests>=2.28
Requires-Dist: urllib3>=1.26
Requires-Dist: cryptography>=41.0
Dynamic: license-file
